bitbucket_mcp_server.py
bitbucket_mcp_server-0.1.2.dist-info/METADATA
bitbucket_mcp_server-0.1.2.dist-info/WHEEL
bitbucket_mcp_server-0.1.2.dist-info/entry_points.txt
bitbucket_mcp_server-0.1.2.dist-info/RECORD
