Metadata-Version: 2.4
Name: bitbucket-mcp-server
Version: 0.1.2
Summary: MCP server for Bitbucket Cloud API integration
Requires-Python: >=3.11
Requires-Dist: aiohttp>=3.12.15
Requires-Dist: mcp>=1.13.1
Requires-Dist: pydantic>=2.11
